open_sandboxes/__init__.py
open_sandboxes/sandbox.py
open_sandboxes/models/__init__.py
open_sandboxes/ssh_connection/__init__.py
open_sandboxes/ssh_connection/base.py
open_sandboxes/uv_config/__init__.py
open_sandboxes/uv_config/config_pyproject.py
open_sandboxes-0.1.0a0.dist-info/METADATA
open_sandboxes-0.1.0a0.dist-info/WHEEL
open_sandboxes-0.1.0a0.dist-info/licenses/LICENSE
open_sandboxes-0.1.0a0.dist-info/RECORD
