Metadata-Version: 2.4
Name: open-sandboxes
Version: 0.1.0a0
Summary: Add your description here
License-File: LICENSE
Requires-Python: >=3.13
Requires-Dist: paramiko>=4.0.0
Requires-Dist: typing-extensions>=4.15.0
